SolSystem/__init__.py
SolSystem/Clients/Client.py
SolSystem/Clients/WebsocketClient.py
SolSystem/Clients/__init__.py
SolSystem/Models/__init__.py
SolSystem/Models/Accounts/Account.py
SolSystem/Models/Accounts/Filters.py
SolSystem/Models/Accounts/VoteAccount.py
SolSystem/Models/Accounts/__init__.py
SolSystem/Models/Accounts/Methods/GetAccountBalance.py
SolSystem/Models/Accounts/Methods/GetAccountInfo.py
SolSystem/Models/Accounts/Methods/GetLargestAccounts.py
SolSystem/Models/Accounts/Methods/GetMinimumBalanceForRentExemption.py
SolSystem/Models/Accounts/Methods/GetMultipleAccounts.py
SolSystem/Models/Accounts/Methods/GetProgramAccounts.py
SolSystem/Models/Accounts/Methods/GetVoteAccounts.py
SolSystem/Models/Blocks/Blocks.py
SolSystem/Models/Blocks/__init__.py
SolSystem/Models/Blocks/Methods/GetBlock.py
SolSystem/Models/Blocks/Methods/GetBlockCommitment.py
SolSystem/Models/Blocks/Methods/GetBlockHeight.py
SolSystem/Models/Blocks/Methods/GetBlockProduction.py
SolSystem/Models/Blocks/Methods/GetBlockTime.py
SolSystem/Models/Blocks/Methods/GetBlocks.py
SolSystem/Models/Blocks/Methods/GetBlocksWithLimit.py
SolSystem/Models/Blocks/Methods/GetFirstAvailableBlock.py
SolSystem/Models/Blocks/Methods/GetLatestBlockhash.py
SolSystem/Models/Blocks/Methods/GetRecentPrioritizationFees.py
SolSystem/Models/Blocks/Methods/IsBlockhashValid.py
SolSystem/Models/Common/Configuration.py
SolSystem/Models/Common/DataTypes.py
SolSystem/Models/Common/Method.py
SolSystem/Models/Common/Response.py
SolSystem/Models/Common/__init__.py
SolSystem/Models/DAS/Asset.py
SolSystem/Models/DAS/HeliusAccount.py
SolSystem/Models/DAS/HeliusAsset.py
SolSystem/Models/DAS/__init__.py
SolSystem/Models/DAS/Methods/GetAsset.py
SolSystem/Models/DAS/Methods/GetTokenAccounts.py
SolSystem/Models/Epoch/Epoch.py
SolSystem/Models/Epoch/__init__.py
SolSystem/Models/Epoch/Methods/GetEpochInfo.py
SolSystem/Models/Epoch/Methods/GetEpochSchedule.py
SolSystem/Models/Inflation/Inflation.py
SolSystem/Models/Inflation/__init__.py
solsystem-1.0.8.dist-info/LICENSE
solsystem-1.0.8.dist-info/METADATA
solsystem-1.0.8.dist-info/WHEEL
solsystem-1.0.8.dist-info/top_level.txt
solsystem-1.0.8.dist-info/RECORD
