Metadata-Version: 2.1
Name: solsystem
Version: 1.0.8
Summary: Type-safe Solana RPC http/websocket API with a focus on Helius and built on Pydantic models.
Author-email: Aleksandr Grin <bytebrushsoftware@gmail.com>
License: MIT
Project-URL: Source, https://github.com/agrin96/solsystem
Keywords: solana,blockchain,web3
Classifier: Programming Language :: Python
Classifier: Programming Language :: Python :: 3
Classifier: Programming Language :: Python :: 3 :: Only
Classifier: Programming Language :: Python :: 3.12
Classifier: Programming Language :: Python :: 3.13
Classifier: Intended Audience :: Developers
Classifier: Intended Audience :: Information Technology
Classifier: Intended Audience :: System Administrators
Classifier: License :: OSI Approved :: MIT License
Classifier: Framework :: Pydantic
Classifier: Topic :: Software Development :: Libraries :: Python Modules
Classifier: Topic :: Internet
Requires-Python: >=3.12
License-File: LICENSE
Requires-Dist: httpx<0.30.0,>=0.27.0
Requires-Dist: pydantic<3.0.0,>=2.7.1
Requires-Dist: pydantic-settings<3.0.0,>=2.2.1
Requires-Dist: termcolor<3.0.0,>=2.4.0
Requires-Dist: base58<3.0.0,>=2.1.1
Requires-Dist: websockets<13.0,>=12.0
